imdb_metadata_extractor/__init__.py
imdb_metadata_extractor/ime.py
imdb_metadata_extractor-0.0.5.dist-info/METADATA
imdb_metadata_extractor-0.0.5.dist-info/WHEEL
imdb_metadata_extractor-0.0.5.dist-info/entry_points.txt
imdb_metadata_extractor-0.0.5.dist-info/top_level.txt
imdb_metadata_extractor-0.0.5.dist-info/RECORD
