Metadata-Version: 2.1
Name: imdb-metadata-extractor
Version: 0.0.5
Summary: imdb-metadata-extractor
Author: Frederico Schmitt Kremer
Author-email: fred.s.kremer@gmail.com
Keywords: web
Requires-Dist: requests
Requires-Dist: requests-html
Requires-Dist: BeautifulSoup4
Requires-Dist: pandas
Requires-Dist: openpyxl
Requires-Dist: twine
